polymatch/__init__.py
polymatch/_version.py
polymatch/base.py
polymatch/error.py
polymatch/py.typed
polymatch/registry.py
polymatch/matchers/__init__.py
polymatch/matchers/glob.py
polymatch/matchers/regex.py
polymatch/matchers/standard.py
polymatch-0.6.0.dist-info/METADATA
polymatch-0.6.0.dist-info/WHEEL
polymatch-0.6.0.dist-info/licenses/LICENSE.txt
polymatch-0.6.0.dist-info/RECORD
