Metadata-Version: 2.4
Name: polymatch
Version: 0.6.0
Summary: A polymorphic pattern matching library for Python
Project-URL: Homepage, https://github.com/TotallyNotRobots/polymatch
Author-email: linuxdaemon <linuxdaemon.irc@gmail.com>
License-Expression: MIT
License-File: LICENSE.txt
Keywords: library,pattern-matching,regex,utility
Classifier: Development Status :: 3 - Alpha
Classifier: License :: OSI Approved :: MIT License
Classifier: Programming Language :: Python :: 3 :: Only
Classifier: Programming Language :: Python :: 3.9
Classifier: Programming Language :: Python :: 3.10
Classifier: Programming Language :: Python :: 3.11
Classifier: Programming Language :: Python :: 3.12
Classifier: Programming Language :: Python :: 3.13
Requires-Python: >=3.9
Requires-Dist: regex
Requires-Dist: typing-extensions
